main.py
pyorganize-1.0.0.dist-info/licenses/LICENSE
pyorganize-1.0.0.dist-info/METADATA
pyorganize-1.0.0.dist-info/WHEEL
pyorganize-1.0.0.dist-info/entry_points.txt
pyorganize-1.0.0.dist-info/top_level.txt
pyorganize-1.0.0.dist-info/RECORD
