Metadata-Version: 2.4
Name: pyorganize
Version: 1.0.0
Summary: A simple file organizer that sorts files into folders by type.
Author-email: "J.P. Ramackers" <jramackers@proton.me>
License: GPL-3.0
Keywords: organize,files,automation
Classifier: Programming Language :: Python :: 3
Classifier: License :: OSI Approved :: GNU General Public License v3 (GPLv3)
Classifier: Operating System :: OS Independent
Requires-Python: >=3.7
License-File: LICENSE
Dynamic: license-file
